{"subreddit":{"display_name":"lua"},"subreddit_loc":"принимать","selftext":"Я не знаю, разрешено ли это здесь, и мне жаль, если это не так, но для моей жизни я не могу понять, Луа. Я буду честен и скажу «да», это домашнее задание для моего класса в колледже, я провел на нем прошлую неделю и поправился, но осталась только одна ошибка, и я не знаю решения. Я не ищу людей, которые сделают мою работу за меня, просто помогите мне понять ошибку и как ее исправить. У меня есть файл C ++, и в нем я использую lua \\ _register следующим образом.\n\nlua \\ _register (player1, \"get \\ _opponent \\ _name\", get \\ _opponent \\ _name);\n\nзатем повторите для плеера 2. оба состояния lua были созданы, и я получаю ошибку при компиляции с указанием недопустимого преобразования из 'std :: \\ _ \\ _ cxx11 :: string (\\ *) (lua \\ _State \\ *)' в Lua \\ _CFunction. что я понял из этого, так это то, что функция get \\ _opponent \\ _name не совместима с lua \\ _CFunction, но другие поняли это? Сама функция занимает всего пятнадцать строк. если бы кто-нибудь мог предоставить где-нибудь, чтобы искать помощь или предложения, я был бы безмерно благодарен!","title":"Нужна помощь с lua_register","subreddit_name_prefixed":"r/lua","ups":4,"created":1552029243,"link_flair_background_color":"","id":"ayj4gr","author":{"name":"Slimjim887"},"permalink":"/r/lua/comments/ayj4gr/need_help_with_lua_register/","url":"https://www.reddit.com/r/lua/comments/ayj4gr/need_help_with_lua_register/","created_utc":1552000443}