{"subreddit":{"display_name":"Bitcoin"},"subreddit_loc":"Bitcoin","selftext":"","title":"Eleven","subreddit_name_prefixed":"r/Bitcoin","ups":3808,"created":1561235898,"link_flair_background_color":"","id":"c3p80e","author":{"name":"jdjdjuuu"},"permalink":"/r/Bitcoin/comments/c3p80e/eleven/","url":"https://i.redd.it/07te6jshxe101.jpg","created_utc":1561207098,"replies":[{"ups":326,"link_id":"t3_c3p80e","replies":[{"ups":41,"link_id":"t3_c3p80e","replies":[{"ups":17,"link_id":"t3_c3p80e","id":"ersuox0","author":"safeandsoundaustin","parent_id":"t1_erstxkq","subreddit_id":"t5_2s3qj","body":"1BTC","body_html":"<div class=\"md\"><p>1BTC</p>\n</div>","permalink":"/r/Bitcoin/comments/c3p80e/eleven/ersuox0/","name":"t1_ersuox0","created":1561253480,"created_utc":1561224680,"subreddit_name_prefixed":"r/Bitcoin","depth":4}],"id":"ersh1or","author":"homeyhomedawg","parent_id":"t1_ersfrk1","subreddit_id":"t5_2s3qj","body":"how much i gotta pay to suck your dick?","body_html":"<div class=\"md\"><p>how much i gotta pay to suck your dick?</p>\n</div>","permalink":"/r/Bitcoin/comments/c3p80e/eleven/ersh1or/","name":"t1_ersh1or","created":1561242615,"created_utc":1561213815,"subreddit_name_prefixed":"r/Bitcoin","depth":2},{"ups":30,"link_id":"t3_c3p80e","replies":[{"ups":6,"link_id":"t3_c3p80e","replies":[{"ups":2,"link_id":"t3_c3p80e","id":"erto5ye","author":"zeeblefritz","parent_id":"t1_ersrhdf","subreddit_id":"t5_2s3qj","body":"Fear me!!!","body_html":"<div class=\"md\"><p>Fear me!!!</p>\n</div>","permalink":"/r/Bitcoin/comments/c3p80e/eleven/erto5ye/","name":"t1_erto5ye","created":1561276934,"created_utc":1561248134,"subreddit_name_prefixed":"r/Bitcoin","depth":6}],"id":"erso8es","author":"Adamsd5","parent_id":"t1_ersg70a","subreddit_id":"t5_2s3qj","body":"God of \"earth\", not \"Earth\".  Could be a very small amount.","body_html":"<div class=\"md\"><p>God of &quot;earth&quot;, not &quot;Earth&quot;.  Could be a very small amount.</p>\n</div>","permalink":"/r/Bitcoin/comments/c3p80e/eleven/erso8es/","name":"t1_erso8es","created":1561248518,"created_utc":1561219718,"subreddit_name_prefixed":"r/Bitcoin","depth":4}],"id":"ersfzzm","author":"crispysuds","parent_id":"t1_ersfrk1","subreddit_id":"t5_2s3qj","body":"Redditor for 2 weeks and already spitting out banger comments like this? Take my upvote","body_html":"<div class=\"md\"><p>Redditor for 2 weeks and already spitting out banger comments like this? Take my upvote</p>\n</div>","permalink":"/r/Bitcoin/comments/c3p80e/eleven/ersfzzm/","name":"t1_ersfzzm","created":1561241695,"created_utc":1561212895,"subreddit_name_prefixed":"r/Bitcoin","depth":2},{"ups":2,"link_id":"t3_c3p80e","id":"ertvpfl","author":"dustobusto","parent_id":"t1_ersfrk1","subreddit_id":"t5_2s3qj","body":"r/iamverysmart","body_html":"<div class=\"md\"><p><a href=\"/r/iamverysmart\">r/iamverysmart</a></p>\n</div>","permalink":"/r/Bitcoin/comments/c3p80e/eleven/ertvpfl/","name":"t1_ertvpfl","created":1561283511,"created_utc":1561254711,"subreddit_name_prefixed":"r/Bitcoin","depth":2},{"ups":1,"link_id":"t3_c3p80e","id":"ertco8s","author":"regin2077","parent_id":"t1_ersfrk1","subreddit_id":"t5_2s3qj","body":"Gfy","body_html":"<div class=\"md\"><p>Gfy</p>\n</div>","permalink":"/r/Bitcoin/comments/c3p80e/eleven/ertco8s/","name":"t1_ertco8s","created":1561267471,"created_utc":1561238671,"subreddit_name_prefixed":"r/Bitcoin","depth":2},{"ups":1,"link_id":"t3_c3p80e","id":"ersjc1f","author":"[deleted]","parent_id":"t1_ersfrk1","subreddit_id":"t5_2s3qj","body":"I'm sorry please just take ~~my money~~ my bitcoin","body_html":"<div class=\"md\"><p>I&#39;m sorry please just take <del>my money</del> my bitcoin</p>\n</div>","permalink":"/r/Bitcoin/comments/c3p80e/eleven/ersjc1f/","name":"t1_ersjc1f","created":1561244559,"created_utc":1561215759,"subreddit_name_prefixed":"r/Bitcoin","depth":2}],"id":"ersapil","author":"vexcoin","parent_id":"t3_c3p80e","subreddit_id":"t5_2s3qj","body":"Just noticed the boxes. lmao. Well done!","body_html":"<div class=\"md\"><p>Just noticed the boxes. lmao. Well done!</p>\n</div>","permalink":"/r/Bitcoin/comments/c3p80e/eleven/ersapil/","name":"t1_ersapil","created":1561236545,"created_utc":1561207745,"subreddit_name_prefixed":"r/Bitcoin","depth":0},{"ups":144,"link_id":"t3_c3p80e","replies":[{"ups":4,"link_id":"t3_c3p80e","id":"ersqfkn","author":"shadowbandit","parent_id":"t1_ersot6e","subreddit_id":"t5_2s3qj","body":"\"Keep In Cold Storage\" lol","body_html":"<div class=\"md\"><p>&quot;Keep In Cold Storage&quot; lol</p>\n</div>","permalink":"/r/Bitcoin/comments/c3p80e/eleven/ersqfkn/","name":"t1_ersqfkn","created":1561250247,"created_utc":1561221447,"subreddit_name_prefixed":"r/Bitcoin","depth":2},{"ups":1,"link_id":"t3_c3p80e","id":"ertbzs2","author":"Walter_Bishop_PhD","parent_id":"t1_ersot6e","subreddit_id":"t5_2s3qj","body":"I'm impressed by the amount of detail that was put into the photoshop","body_html":"<div class=\"md\"><p>I&#39;m impressed by the amount of detail that was put into the photoshop</p>\n</div>","permalink":"/r/Bitcoin/comments/c3p80e/eleven/ertbzs2/","name":"t1_ertbzs2","created":1561266935,"created_utc":1561238135,"subreddit_name_prefixed":"r/Bitcoin","depth":2}],"id":"ersb605","author":"jdjdjuuu","parent_id":"t3_c3p80e","subreddit_id":"t5_2s3qj","body":"credit to the original from last run up: [https://www.reddit.com/r/Bitcoin/comments/7gzr64/eleven/](https://www.reddit.com/r/Bitcoin/comments/7gzr64/eleven/)","body_html":"<div class=\"md\"><p>credit to the original from last run up: <a href=\"https://www.reddit.com/r/Bitcoin/comments/7gzr64/eleven/\">https://www.reddit.com/r/Bitcoin/comments/7gzr64/eleven/</a></p>\n</div>","permalink":"/r/Bitcoin/comments/c3p80e/eleven/ersb605/","name":"t1_ersb605","created":1561237037,"created_utc":1561208237,"subreddit_name_prefixed":"r/Bitcoin","depth":0},{"ups":68,"link_id":"t3_c3p80e","replies":[{"ups":17,"link_id":"t3_c3p80e","replies":[{"ups":4,"link_id":"t3_c3p80e","replies":[{"ups":1,"link_id":"t3_c3p80e","replies":[{"ups":1,"link_id":"t3_c3p80e","id":"ertc58k","author":"xddm2653","parent_id":"t1_ertbqrn","subreddit_id":"t5_2s3qj","body":"Yea that's just lazy. Plenty of individual ones do. And cryptocurrency as a whole doesn't outperform the market either so maybe you shouldn't be in BTC","body_html":"<div class=\"md\"><p>Yea that&#39;s just lazy. Plenty of individual ones do. And cryptocurrency as a whole doesn&#39;t outperform the market either so maybe you shouldn&#39;t be in BTC</p>\n</div>","permalink":"/r/Bitcoin/comments/c3p80e/eleven/ertc58k/","name":"t1_ertc58k","created":1561267059,"created_utc":1561238259,"subreddit_name_prefixed":"r/Bitcoin","depth":8}],"id":"ertavmj","author":"xddm2653","parent_id":"t1_ersuk36","subreddit_id":"t5_2s3qj","body":"lmao those scrubs would criticize you for investing in an actively managed fund. Its all in VTI or gtfo","body_html":"<div class=\"md\"><p>lmao those scrubs would criticize you for investing in an actively managed fund. Its all in VTI or gtfo</p>\n</div>","permalink":"/r/Bitcoin/comments/c3p80e/eleven/ertavmj/","name":"t1_ertavmj","created":1561266051,"created_utc":1561237251,"subreddit_name_prefixed":"r/Bitcoin","depth":6}],"id":"ersu3xj","author":"tob23ler","parent_id":"t1_ersqyfm","subreddit_id":"t5_2s3qj","body":"Some are risk averse, yes. But perhaps you haven't seen or met the plethora of true haters. They exist, and they're spectacular","body_html":"<div class=\"md\"><p>Some are risk averse, yes. But perhaps you haven&#39;t seen or met the plethora of true haters. They exist, and they&#39;re spectacular</p>\n</div>","permalink":"/r/Bitcoin/comments/c3p80e/eleven/ersu3xj/","name":"t1_ersu3xj","created":1561253048,"created_utc":1561224248,"subreddit_name_prefixed":"r/Bitcoin","depth":4},{"ups":0,"link_id":"t3_c3p80e","id":"ersualg","author":"Yegie","parent_id":"t1_ersqyfm","subreddit_id":"t5_2s3qj","body":"Did someone mention naked calls?","body_html":"<div class=\"md\"><p>Did someone mention naked calls?</p>\n</div>","permalink":"/r/Bitcoin/comments/c3p80e/eleven/ersualg/","name":"t1_ersualg","created":1561253188,"created_utc":1561224388,"subreddit_name_prefixed":"r/Bitcoin","depth":4}],"id":"erslrq9","author":"Starkgaryen69","parent_id":"t1_ersjgax","subreddit_id":"t5_2s3qj","body":"Still in the comment section lots people spew shit. They can’t stand Bitcoin or its community, kind of sad. Oh well.","body_html":"<div class=\"md\"><p>Still in the comment section lots people spew shit. They can’t stand Bitcoin or its community, kind of sad. Oh well.</p>\n</div>","permalink":"/r/Bitcoin/comments/c3p80e/eleven/erslrq9/","name":"t1_erslrq9","created":1561246560,"created_utc":1561217760,"subreddit_name_prefixed":"r/Bitcoin","depth":2}],"id":"erse5o4","author":"SpontaneousDream","parent_id":"t3_c3p80e","subreddit_id":"t5_2s3qj","body":"/r/investing on suicide watch","body_html":"<div class=\"md\"><p><a href=\"/r/investing\">/r/investing</a> on suicide watch</p>\n</div>","permalink":"/r/Bitcoin/comments/c3p80e/eleven/erse5o4/","name":"t1_erse5o4","created":1561240036,"created_utc":1561211236,"subreddit_name_prefixed":"r/Bitcoin","depth":0},{"ups":78,"link_id":"t3_c3p80e","replies":[{"ups":5,"link_id":"t3_c3p80e","id":"ersqiyt","author":"hail_to_the_beef","parent_id":"t1_ersg8z5","subreddit_id":"t5_2s3qj","body":"You’re like many fomo buyers. Don’t worry you’ll make gains in due time.","body_html":"<div class=\"md\"><p>You’re like many fomo buyers. Don’t worry you’ll make gains in due time.</p>\n</div>","permalink":"/r/Bitcoin/comments/c3p80e/eleven/ersqiyt/","name":"t1_ersqiyt","created":1561250316,"created_utc":1561221516,"subreddit_name_prefixed":"r/Bitcoin","depth":2}],"id":"ersag59","author":"HodlMyMoon","parent_id":"t3_c3p80e","subreddit_id":"t5_2s3qj","body":"Currently jizzing in my pants. For once I get to relax while everyone flips out trying to get money into the market. Thank fucking god I have been buying for awhile now because FOMO would have been EATING ME ALIVE... now I can kick back and watch what happens.","body_html":"<div class=\"md\"><p>Currently jizzing in my pants. For once I get to relax while everyone flips out trying to get money into the market. Thank fucking god I have been buying for awhile now because FOMO would have been EATING ME ALIVE... now I can kick back and watch what happens.</p>\n</div>","permalink":"/r/Bitcoin/comments/c3p80e/eleven/ersag59/","name":"t1_ersag59","created":1561236257,"created_utc":1561207457,"subreddit_name_prefixed":"r/Bitcoin","depth":0},{"ups":18,"link_id":"t3_c3p80e","id":"ersaf7e","author":"3rdeyeopenwide","parent_id":"t3_c3p80e","subreddit_id":"t5_2s3qj","body":"There it is.","body_html":"<div class=\"md\"><p>There it is.</p>\n</div>","permalink":"/r/Bitcoin/comments/c3p80e/eleven/ersaf7e/","name":"t1_ersaf7e","created":1561236229,"created_utc":1561207429,"subreddit_name_prefixed":"r/Bitcoin","depth":0},{"ups":8,"link_id":"t3_c3p80e","id":"ersgi93","author":"masterjolly","parent_id":"t3_c3p80e","subreddit_id":"t5_2s3qj","body":"Holy shit. I thought you were just posting the meme in preparation for 11k. I open CMC and see Bitcoin actually surpassed 11K! WTF. This is crazy.","body_html":"<div class=\"md\"><p>Holy shit. I thought you were just posting the meme in preparation for 11k. I open CMC and see Bitcoin actually surpassed 11K! WTF. This is crazy.</p>\n</div>","permalink":"/r/Bitcoin/comments/c3p80e/eleven/ersgi93/","name":"t1_ersgi93","created":1561242146,"created_utc":1561213346,"subreddit_name_prefixed":"r/Bitcoin","depth":0},{"ups":13,"link_id":"t3_c3p80e","id":"ersc59b","author":"8B4L","parent_id":"t3_c3p80e","subreddit_id":"t5_2s3qj","body":"And not one thing is strange about it.","body_html":"<div class=\"md\"><p>And not one thing is strange about it.</p>\n</div>","permalink":"/r/Bitcoin/comments/c3p80e/eleven/ersc59b/","name":"t1_ersc59b","created":1561238061,"created_utc":1561209261,"subreddit_name_prefixed":"r/Bitcoin","depth":0},{"ups":8,"link_id":"t3_c3p80e","id":"erscl0z","author":"Ryan1188","parent_id":"t3_c3p80e","subreddit_id":"t5_2s3qj","body":"I can't unsee the \"eggo\" on the box on the left....but for some reason it was done on the box on the right.","body_html":"<div class=\"md\"><p>I can&#39;t unsee the &quot;eggo&quot; on the box on the left....but for some reason it was done on the box on the right.</p>\n</div>","permalink":"/r/Bitcoin/comments/c3p80e/eleven/erscl0z/","name":"t1_erscl0z","created":1561238503,"created_utc":1561209703,"subreddit_name_prefixed":"r/Bitcoin","depth":0},{"ups":28,"link_id":"t3_c3p80e","replies":[{"ups":1,"link_id":"t3_c3p80e","id":"ersqu8n","author":"shadowbandit","parent_id":"t1_ersh9gq","subreddit_id":"t5_2s3qj","body":"...the syrup!  \n \nShake (the weak) and bake (fresh ATHs)","body_html":"<div class=\"md\"><p>...the syrup!  </p>\n\n<p>Shake (the weak) and bake (fresh ATHs)</p>\n</div>","permalink":"/r/Bitcoin/comments/c3p80e/eleven/ersqu8n/","name":"t1_ersqu8n","created":1561250551,"created_utc":1561221751,"subreddit_name_prefixed":"r/Bitcoin","depth":2}],"id":"erscb83","author":"J-Dead","parent_id":"t3_c3p80e","subreddit_id":"t5_2s3qj","body":"What's the reason for btc going up?","body_html":"<div class=\"md\"><p>What&#39;s the reason for btc going up?</p>\n</div>","permalink":"/r/Bitcoin/comments/c3p80e/eleven/erscb83/","name":"t1_erscb83","created":1561238231,"created_utc":1561209431,"subreddit_name_prefixed":"r/Bitcoin","depth":0},{"ups":6,"link_id":"t3_c3p80e","id":"ersigos","author":"SatanicSpambot","parent_id":"t3_c3p80e","subreddit_id":"t5_2s3qj","body":"As someone with less than a quarter of btc. PLEASE STAAAAHP","body_html":"<div class=\"md\"><p>As someone with less than a quarter of btc. PLEASE STAAAAHP</p>\n</div>","permalink":"/r/Bitcoin/comments/c3p80e/eleven/ersigos/","name":"t1_ersigos","created":1561243823,"created_utc":1561215023,"subreddit_name_prefixed":"r/Bitcoin","depth":0},{"ups":4,"link_id":"t3_c3p80e","id":"ersg2gv","author":"MechAegis","parent_id":"t3_c3p80e","subreddit_id":"t5_2s3qj","body":"WTH man...last night I saw it at 9.1k.\n\nThis morning I wake up to see it at 11k.","body_html":"<div class=\"md\"><p>WTH man...last night I saw it at 9.1k.</p>\n\n<p>This morning I wake up to see it at 11k.</p>\n</div>","permalink":"/r/Bitcoin/comments/c3p80e/eleven/ersg2gv/","name":"t1_ersg2gv","created":1561241757,"created_utc":1561212957,"subreddit_name_prefixed":"r/Bitcoin","depth":0},{"ups":10,"link_id":"t3_c3p80e","replies":[{"ups":4,"link_id":"t3_c3p80e","id":"ersxggr","author":"ducksauce88","parent_id":"t1_ersxc6k","subreddit_id":"t5_2s3qj","body":"I am. $10,700 ???","body_html":"<div class=\"md\"><p>I am. $10,700 ???</p>\n</div>","permalink":"/r/Bitcoin/comments/c3p80e/eleven/ersxggr/","name":"t1_ersxggr","created":1561255562,"created_utc":1561226762,"subreddit_name_prefixed":"r/Bitcoin","depth":2}],"id":"ersiil2","author":"ducksauce88","parent_id":"t3_c3p80e","subreddit_id":"t5_2s3qj","body":"Annnndddd it's gone. Way to go guys 🤣🤣","body_html":"<div class=\"md\"><p>Annnndddd it&#39;s gone. Way to go guys 🤣🤣</p>\n</div>","permalink":"/r/Bitcoin/comments/c3p80e/eleven/ersiil2/","name":"t1_ersiil2","created":1561243868,"created_utc":1561215068,"subreddit_name_prefixed":"r/Bitcoin","depth":0},{"ups":5,"link_id":"t3_c3p80e","id":"ersf9df","author":"ethfiend2064","parent_id":"t3_c3p80e","subreddit_id":"t5_2s3qj","body":"Man, this is one of the best shitposts in a Long Time :-)","body_html":"<div class=\"md\"><p>Man, this is one of the best shitposts in a Long Time :-)</p>\n</div>","permalink":"/r/Bitcoin/comments/c3p80e/eleven/ersf9df/","name":"t1_ersf9df","created":1561241042,"created_utc":1561212242,"subreddit_name_prefixed":"r/Bitcoin","depth":0},{"ups":5,"link_id":"t3_c3p80e","id":"ersw437","author":"[deleted]","parent_id":"t3_c3p80e","subreddit_id":"t5_2s3qj","body":"So is Bitcoin still a scam and are we better off with a centralised currency?\n\n&#x200B;\n\nThoughts?","body_html":"<div class=\"md\"><p>So is Bitcoin still a scam and are we better off with a centralised currency?</p>\n\n<p>&#x200B;</p>\n\n<p>Thoughts?</p>\n</div>","permalink":"/r/Bitcoin/comments/c3p80e/eleven/ersw437/","name":"t1_ersw437","created":1561254545,"created_utc":1561225745,"subreddit_name_prefixed":"r/Bitcoin","depth":0},{"ups":3,"link_id":"t3_c3p80e","replies":[{"ups":3,"link_id":"t3_c3p80e","id":"ersi6kr","author":"peencheputo","parent_id":"t1_ershyji","subreddit_id":"t5_2s3qj","body":"I hope. I sold at the plummet and bought back in in the uptick!","body_html":"<div class=\"md\"><p>I hope. I sold at the plummet and bought back in in the uptick!</p>\n</div>","permalink":"/r/Bitcoin/comments/c3p80e/eleven/ersi6kr/","name":"t1_ersi6kr","created":1561243583,"created_utc":1561214783,"subreddit_name_prefixed":"r/Bitcoin","depth":2}],"id":"ershpd9","author":"peencheputo","parent_id":"t3_c3p80e","subreddit_id":"t5_2s3qj","body":"And it’s gone","body_html":"<div class=\"md\"><p>And it’s gone</p>\n</div>","permalink":"/r/Bitcoin/comments/c3p80e/eleven/ershpd9/","name":"t1_ershpd9","created":1561243178,"created_utc":1561214378,"subreddit_name_prefixed":"r/Bitcoin","depth":0},{"ups":3,"link_id":"t3_c3p80e","id":"eruaf89","author":"Aggravating_Cream","parent_id":"t3_c3p80e","subreddit_id":"t5_2s3qj","body":"Didn't last long at $11000 though","body_html":"<div class=\"md\"><p>Didn&#39;t last long at $11000 though</p>\n</div>","permalink":"/r/Bitcoin/comments/c3p80e/eleven/eruaf89/","name":"t1_eruaf89","created":1561298267,"created_utc":1561269467,"subreddit_name_prefixed":"r/Bitcoin","depth":0},{"ups":5,"link_id":"t3_c3p80e","id":"ershdum","author":"DammitLeeroyPokemon","parent_id":"t3_c3p80e","subreddit_id":"t5_2s3qj","body":"....and now it's back down to 10.5, are you happy?!\n\nedit - 10.2 fuck","body_html":"<div class=\"md\"><p>....and now it&#39;s back down to 10.5, are you happy?!</p>\n\n<p>edit - 10.2 fuck</p>\n</div>","permalink":"/r/Bitcoin/comments/c3p80e/eleven/ershdum/","name":"t1_ershdum","created":1561242905,"created_utc":1561214105,"subreddit_name_prefixed":"r/Bitcoin","depth":0},{"ups":2,"link_id":"t3_c3p80e","id":"ersaj75","author":"slartibartjars","parent_id":"t3_c3p80e","subreddit_id":"t5_2s3qj","body":"golf clap","body_html":"<div class=\"md\"><p>golf clap</p>\n</div>","permalink":"/r/Bitcoin/comments/c3p80e/eleven/ersaj75/","name":"t1_ersaj75","created":1561236353,"created_utc":1561207553,"subreddit_name_prefixed":"r/Bitcoin","depth":0},{"ups":2,"link_id":"t3_c3p80e","id":"ersb276","author":"N8twon","parent_id":"t3_c3p80e","subreddit_id":"t5_2s3qj","body":"I fux with this","body_html":"<div class=\"md\"><p>I fux with this</p>\n</div>","permalink":"/r/Bitcoin/comments/c3p80e/eleven/ersb276/","name":"t1_ersb276","created":1561236924,"created_utc":1561208124,"subreddit_name_prefixed":"r/Bitcoin","depth":0},{"ups":2,"link_id":"t3_c3p80e","id":"ersevhx","author":"RetroRocket80","parent_id":"t3_c3p80e","subreddit_id":"t5_2s3qj","body":"Turn it up to 11","body_html":"<div class=\"md\"><p>Turn it up to 11</p>\n</div>","permalink":"/r/Bitcoin/comments/c3p80e/eleven/ersevhx/","name":"t1_ersevhx","created":1561240699,"created_utc":1561211899,"subreddit_name_prefixed":"r/Bitcoin","depth":0},{"ups":2,"link_id":"t3_c3p80e","id":"ersgjg3","author":"DisconcertingBending","parent_id":"t3_c3p80e","subreddit_id":"t5_2s3qj","body":"😂","body_html":"<div class=\"md\"><p>😂</p>\n</div>","permalink":"/r/Bitcoin/comments/c3p80e/eleven/ersgjg3/","name":"t1_ersgjg3","created":1561242176,"created_utc":1561213376,"subreddit_name_prefixed":"r/Bitcoin","depth":0},{"ups":2,"link_id":"t3_c3p80e","id":"ersi0zq","author":"blubaconbuffalo","parent_id":"t3_c3p80e","subreddit_id":"t5_2s3qj","body":"This is fking gold! Great job lol","body_html":"<div class=\"md\"><p>This is fking gold! Great job lol</p>\n</div>","permalink":"/r/Bitcoin/comments/c3p80e/eleven/ersi0zq/","name":"t1_ersi0zq","created":1561243452,"created_utc":1561214652,"subreddit_name_prefixed":"r/Bitcoin","depth":0},{"ups":2,"link_id":"t3_c3p80e","id":"ersss55","author":"Narradisall","parent_id":"t3_c3p80e","subreddit_id":"t5_2s3qj","body":"Enjoying the memes coming back.\n\nTo the moon in Lambos!","body_html":"<div class=\"md\"><p>Enjoying the memes coming back.</p>\n\n<p>To the moon in Lambos!</p>\n</div>","permalink":"/r/Bitcoin/comments/c3p80e/eleven/ersss55/","name":"t1_ersss55","created":1561252025,"created_utc":1561223225,"subreddit_name_prefixed":"r/Bitcoin","depth":0},{"ups":2,"link_id":"t3_c3p80e","id":"ert9biy","author":"ebaley","parent_id":"t3_c3p80e","subreddit_id":"t5_2s3qj","body":"Stranger things have been known to happen.","body_html":"<div class=\"md\"><p>Stranger things have been known to happen.</p>\n</div>","permalink":"/r/Bitcoin/comments/c3p80e/eleven/ert9biy/","name":"t1_ert9biy","created":1561264830,"created_utc":1561236030,"subreddit_name_prefixed":"r/Bitcoin","depth":0},{"ups":2,"link_id":"t3_c3p80e","id":"erta0ld","author":"tranceology3","parent_id":"t3_c3p80e","subreddit_id":"t5_2s3qj","body":"Wow this is great photoshop skills.....or did Stranger Things actually do this scene with real Bitcoin boxes...hmm","body_html":"<div class=\"md\"><p>Wow this is great photoshop skills.....or did Stranger Things actually do this scene with real Bitcoin boxes...hmm</p>\n</div>","permalink":"/r/Bitcoin/comments/c3p80e/eleven/erta0ld/","name":"t1_erta0ld","created":1561265374,"created_utc":1561236574,"subreddit_name_prefixed":"r/Bitcoin","depth":0},{"ups":2,"link_id":"t3_c3p80e","id":"eruam6z","author":"flictsyss31","parent_id":"t3_c3p80e","subreddit_id":"t5_2s3qj","body":"Going once, Going twice, Going Thrice, Going Up Forever!","body_html":"<div class=\"md\"><p>Going once, Going twice, Going Thrice, Going Up Forever!</p>\n</div>","permalink":"/r/Bitcoin/comments/c3p80e/eleven/eruam6z/","name":"t1_eruam6z","created":1561298514,"created_utc":1561269714,"subreddit_name_prefixed":"r/Bitcoin","depth":0},{"ups":2,"link_id":"t3_c3p80e","id":"ersaajk","author":"ItIsABigManThing","parent_id":"t3_c3p80e","subreddit_id":"t5_2s3qj","body":"Lol","body_html":"<div class=\"md\"><p>Lol</p>\n</div>","permalink":"/r/Bitcoin/comments/c3p80e/eleven/ersaajk/","name":"t1_ersaajk","created":1561236090,"created_utc":1561207290,"subreddit_name_prefixed":"r/Bitcoin","depth":0},{"ups":1,"link_id":"t3_c3p80e","id":"ersc60e","author":"Jonas1312","parent_id":"t3_c3p80e","subreddit_id":"t5_2s3qj","body":"Awesome! But this is not the end","body_html":"<div class=\"md\"><p>Awesome! But this is not the end</p>\n</div>","permalink":"/r/Bitcoin/comments/c3p80e/eleven/ersc60e/","name":"t1_ersc60e","created":1561238082,"created_utc":1561209282,"subreddit_name_prefixed":"r/Bitcoin","depth":0},{"ups":1,"link_id":"t3_c3p80e","id":"erscx22","author":"emichael86","parent_id":"t3_c3p80e","subreddit_id":"t5_2s3qj","body":"Well played!","body_html":"<div class=\"md\"><p>Well played!</p>\n</div>","permalink":"/r/Bitcoin/comments/c3p80e/eleven/erscx22/","name":"t1_erscx22","created":1561238837,"created_utc":1561210037,"subreddit_name_prefixed":"r/Bitcoin","depth":0},{"ups":1,"link_id":"t3_c3p80e","id":"ersdfij","author":"lisa_lionheart","parent_id":"t3_c3p80e","subreddit_id":"t5_2s3qj","body":"What's the BTCEGGOS rate?","body_html":"<div class=\"md\"><p>What&#39;s the BTCEGGOS rate?</p>\n</div>","permalink":"/r/Bitcoin/comments/c3p80e/eleven/ersdfij/","name":"t1_ersdfij","created":1561239345,"created_utc":1561210545,"subreddit_name_prefixed":"r/Bitcoin","depth":0},{"ups":1,"link_id":"t3_c3p80e","id":"ersdyp0","author":"j_remy11","parent_id":"t3_c3p80e","subreddit_id":"t5_2s3qj","body":"we're back boys!","body_html":"<div class=\"md\"><p>we&#39;re back boys!</p>\n</div>","permalink":"/r/Bitcoin/comments/c3p80e/eleven/ersdyp0/","name":"t1_ersdyp0","created":1561239855,"created_utc":1561211055,"subreddit_name_prefixed":"r/Bitcoin","depth":0},{"ups":1,"link_id":"t3_c3p80e","id":"erse5tu","author":"MarkOates","parent_id":"t3_c3p80e","subreddit_id":"t5_2s3qj","body":"omg that's a really good meme","body_html":"<div class=\"md\"><p>omg that&#39;s a really good meme</p>\n</div>","permalink":"/r/Bitcoin/comments/c3p80e/eleven/erse5tu/","name":"t1_erse5tu","created":1561240040,"created_utc":1561211240,"subreddit_name_prefixed":"r/Bitcoin","depth":0},{"ups":1,"link_id":"t3_c3p80e","id":"ersecqf","author":"IsmaelRami","parent_id":"t3_c3p80e","subreddit_id":"t5_2s3qj","body":"It's funny cause it is true XD","body_html":"<div class=\"md\"><p>It&#39;s funny cause it is true XD</p>\n</div>","permalink":"/r/Bitcoin/comments/c3p80e/eleven/ersecqf/","name":"t1_ersecqf","created":1561240219,"created_utc":1561211419,"subreddit_name_prefixed":"r/Bitcoin","depth":0},{"ups":1,"link_id":"t3_c3p80e","id":"ersefc9","author":"Ineedmorebtc","parent_id":"t3_c3p80e","subreddit_id":"t5_2s3qj","body":"Leggo my Bitcoin!","body_html":"<div class=\"md\"><p>Leggo my Bitcoin!</p>\n</div>","permalink":"/r/Bitcoin/comments/c3p80e/eleven/ersefc9/","name":"t1_ersefc9","created":1561240285,"created_utc":1561211485,"subreddit_name_prefixed":"r/Bitcoin","depth":0},{"ups":1,"link_id":"t3_c3p80e","id":"ersehjb","author":"Kfeugos","parent_id":"t3_c3p80e","subreddit_id":"t5_2s3qj","body":"See ya in hot","body_html":"<div class=\"md\"><p>See ya in hot</p>\n</div>","permalink":"/r/Bitcoin/comments/c3p80e/eleven/ersehjb/","name":"t1_ersehjb","created":1561240343,"created_utc":1561211543,"subreddit_name_prefixed":"r/Bitcoin","depth":0},{"ups":1,"link_id":"t3_c3p80e","id":"ersfojy","author":"jhcrypto17","parent_id":"t3_c3p80e","subreddit_id":"t5_2s3qj","body":"Ha lv this","body_html":"<div class=\"md\"><p>Ha lv this</p>\n</div>","permalink":"/r/Bitcoin/comments/c3p80e/eleven/ersfojy/","name":"t1_ersfojy","created":1561241415,"created_utc":1561212615,"subreddit_name_prefixed":"r/Bitcoin","depth":0},{"ups":1,"link_id":"t3_c3p80e","id":"ersfvhl","author":"yogibreakdance","parent_id":"t3_c3p80e","subreddit_id":"t5_2s3qj","body":"Better take astrology online classes guys. Moon coming.","body_html":"<div class=\"md\"><p>Better take astrology online classes guys. Moon coming.</p>\n</div>","permalink":"/r/Bitcoin/comments/c3p80e/eleven/ersfvhl/","name":"t1_ersfvhl","created":1561241586,"created_utc":1561212786,"subreddit_name_prefixed":"r/Bitcoin","depth":0},{"ups":1,"link_id":"t3_c3p80e","id":"ersfwof","author":"PartyMan911","parent_id":"t3_c3p80e","subreddit_id":"t5_2s3qj","body":"Hodl til 11 million","body_html":"<div class=\"md\"><p>Hodl til 11 million</p>\n</div>","permalink":"/r/Bitcoin/comments/c3p80e/eleven/ersfwof/","name":"t1_ersfwof","created":1561241617,"created_utc":1561212817,"subreddit_name_prefixed":"r/Bitcoin","depth":0},{"ups":1,"link_id":"t3_c3p80e","id":"ersgl5h","author":"slardybartfast8","parent_id":"t3_c3p80e","subreddit_id":"t5_2s3qj","body":"And the award for best new meme goes to.../u/jdjdjuuu","body_html":"<div class=\"md\"><p>And the award for best new meme goes to...<a href=\"/u/jdjdjuuu\">/u/jdjdjuuu</a></p>\n</div>","permalink":"/r/Bitcoin/comments/c3p80e/eleven/ersgl5h/","name":"t1_ersgl5h","created":1561242218,"created_utc":1561213418,"subreddit_name_prefixed":"r/Bitcoin","depth":0},{"ups":1,"link_id":"t3_c3p80e","id":"ersgm7i","author":"rostercamp","parent_id":"t3_c3p80e","subreddit_id":"t5_2s3qj","body":"this is awesome. Kudos","body_html":"<div class=\"md\"><p>this is awesome. Kudos</p>\n</div>","permalink":"/r/Bitcoin/comments/c3p80e/eleven/ersgm7i/","name":"t1_ersgm7i","created":1561242244,"created_utc":1561213444,"subreddit_name_prefixed":"r/Bitcoin","depth":0},{"ups":1,"link_id":"t3_c3p80e","id":"ersjcrn","author":"Henrythe1st","parent_id":"t3_c3p80e","subreddit_id":"t5_2s3qj","body":"Goodone","body_html":"<div class=\"md\"><p>Goodone</p>\n</div>","permalink":"/r/Bitcoin/comments/c3p80e/eleven/ersjcrn/","name":"t1_ersjcrn","created":1561244575,"created_utc":1561215775,"subreddit_name_prefixed":"r/Bitcoin","depth":0},{"ups":1,"link_id":"t3_c3p80e","id":"ersm69o","author":"opencoins","parent_id":"t3_c3p80e","subreddit_id":"t5_2s3qj","body":"Can someone explain this meme?","body_html":"<div class=\"md\"><p>Can someone explain this meme?</p>\n</div>","permalink":"/r/Bitcoin/comments/c3p80e/eleven/ersm69o/","name":"t1_ersm69o","created":1561246879,"created_utc":1561218079,"subreddit_name_prefixed":"r/Bitcoin","depth":0},{"ups":1,"link_id":"t3_c3p80e","id":"ersnrpx","author":"brereddit","parent_id":"t3_c3p80e","subreddit_id":"t5_2s3qj","body":"Clever.","body_html":"<div class=\"md\"><p>Clever.</p>\n</div>","permalink":"/r/Bitcoin/comments/c3p80e/eleven/ersnrpx/","name":"t1_ersnrpx","created":1561248147,"created_utc":1561219347,"subreddit_name_prefixed":"r/Bitcoin","depth":0},{"ups":1,"link_id":"t3_c3p80e","id":"erssnjr","author":"inchhigh314","parent_id":"t3_c3p80e","subreddit_id":"t5_2s3qj","body":"Freedom! Scotland!!!\n\nhttps://youtu.be/J3lYLphzAnw","body_html":"<div class=\"md\"><p>Freedom! Scotland!!!</p>\n\n<p><a href=\"https://youtu.be/J3lYLphzAnw\">https://youtu.be/J3lYLphzAnw</a></p>\n</div>","permalink":"/r/Bitcoin/comments/c3p80e/eleven/erssnjr/","name":"t1_erssnjr","created":1561251927,"created_utc":1561223127,"subreddit_name_prefixed":"r/Bitcoin","depth":0},{"ups":1,"link_id":"t3_c3p80e","id":"erssz65","author":"derektrader7","parent_id":"t3_c3p80e","subreddit_id":"t5_2s3qj","body":"I really missed this meme. It's like we spent forever waiting toy say over 9000 now we're flying past 10k 11k. Feels really good to be a Hodler for the first time in a while","body_html":"<div class=\"md\"><p>I really missed this meme. It&#39;s like we spent forever waiting toy say over 9000 now we&#39;re flying past 10k 11k. Feels really good to be a Hodler for the first time in a while</p>\n</div>","permalink":"/r/Bitcoin/comments/c3p80e/eleven/erssz65/","name":"t1_erssz65","created":1561252175,"created_utc":1561223375,"subreddit_name_prefixed":"r/Bitcoin","depth":0},{"ups":1,"link_id":"t3_c3p80e","id":"ersul2p","author":"safeandsoundaustin","parent_id":"t3_c3p80e","subreddit_id":"t5_2s3qj","body":"No spinal tap memes? “This one goes to 11”","body_html":"<div class=\"md\"><p>No spinal tap memes? “This one goes to 11”</p>\n</div>","permalink":"/r/Bitcoin/comments/c3p80e/eleven/ersul2p/","name":"t1_ersul2p","created":1561253404,"created_utc":1561224604,"subreddit_name_prefixed":"r/Bitcoin","depth":0},{"ups":1,"link_id":"t3_c3p80e","id":"ersy1nj","author":"AllLightsFuckedd","parent_id":"t3_c3p80e","subreddit_id":"t5_2s3qj","body":"🦀🦀11k🦀🦀","body_html":"<div class=\"md\"><p>🦀🦀11k🦀🦀</p>\n</div>","permalink":"/r/Bitcoin/comments/c3p80e/eleven/ersy1nj/","name":"t1_ersy1nj","created":1561256014,"created_utc":1561227214,"subreddit_name_prefixed":"r/Bitcoin","depth":0},{"ups":1,"link_id":"t3_c3p80e","id":"erszm3s","author":"Sippaa","parent_id":"t3_c3p80e","subreddit_id":"t5_2s3qj","body":"This is Gold.","body_html":"<div class=\"md\"><p>This is Gold.</p>\n</div>","permalink":"/r/Bitcoin/comments/c3p80e/eleven/erszm3s/","name":"t1_erszm3s","created":1561257210,"created_utc":1561228410,"subreddit_name_prefixed":"r/Bitcoin","depth":0},{"ups":1,"link_id":"t3_c3p80e","id":"ert66xr","author":"pietiose","parent_id":"t3_c3p80e","subreddit_id":"t5_2s3qj","body":"Actually came to the sub to see her, was not disappointed","body_html":"<div class=\"md\"><p>Actually came to the sub to see her, was not disappointed</p>\n</div>","permalink":"/r/Bitcoin/comments/c3p80e/eleven/ert66xr/","name":"t1_ert66xr","created":1561262336,"created_utc":1561233536,"subreddit_name_prefixed":"r/Bitcoin","depth":0},{"ups":1,"link_id":"t3_c3p80e","id":"ert6xxh","author":"Velhoconhecido","parent_id":"t3_c3p80e","subreddit_id":"t5_2s3qj","body":"AGAIN","body_html":"<div class=\"md\"><p>AGAIN</p>\n</div>","permalink":"/r/Bitcoin/comments/c3p80e/eleven/ert6xxh/","name":"t1_ert6xxh","created":1561262944,"created_utc":1561234144,"subreddit_name_prefixed":"r/Bitcoin","depth":0},{"ups":1,"link_id":"t3_c3p80e","id":"ert9nkz","author":"tlmzn4","parent_id":"t3_c3p80e","subreddit_id":"t5_2s3qj","body":"Wow","body_html":"<div class=\"md\"><p>Wow</p>\n</div>","permalink":"/r/Bitcoin/comments/c3p80e/eleven/ert9nkz/","name":"t1_ert9nkz","created":1561265088,"created_utc":1561236288,"subreddit_name_prefixed":"r/Bitcoin","depth":0},{"ups":1,"link_id":"t3_c3p80e","id":"ertkmnk","author":"linkinpark9503","parent_id":"t3_c3p80e","subreddit_id":"t5_2s3qj","body":"Wish I would have bought more at Christmas 🤦‍♀️🤦‍♀️🤦‍♀️","body_html":"<div class=\"md\"><p>Wish I would have bought more at Christmas 🤦‍♀️🤦‍♀️🤦‍♀️</p>\n</div>","permalink":"/r/Bitcoin/comments/c3p80e/eleven/ertkmnk/","name":"t1_ertkmnk","created":1561273934,"created_utc":1561245134,"subreddit_name_prefixed":"r/Bitcoin","depth":0},{"ups":1,"link_id":"t3_c3p80e","id":"ertlfeh","author":"AkusMMM","parent_id":"t3_c3p80e","subreddit_id":"t5_2s3qj","body":"Is Scarlett playing a boy in this new movie?","body_html":"<div class=\"md\"><p>Is Scarlett playing a boy in this new movie?</p>\n</div>","permalink":"/r/Bitcoin/comments/c3p80e/eleven/ertlfeh/","name":"t1_ertlfeh","created":1561274613,"created_utc":1561245813,"subreddit_name_prefixed":"r/Bitcoin","depth":0},{"ups":1,"link_id":"t3_c3p80e","id":"ertoobh","author":"anilukespop","parent_id":"t3_c3p80e","subreddit_id":"t5_2s3qj","body":"Yay!","body_html":"<div class=\"md\"><p>Yay!</p>\n</div>","permalink":"/r/Bitcoin/comments/c3p80e/eleven/ertoobh/","name":"t1_ertoobh","created":1561277367,"created_utc":1561248567,"subreddit_name_prefixed":"r/Bitcoin","depth":0},{"ups":1,"link_id":"t3_c3p80e","id":"ertqb2y","author":"sneeeks","parent_id":"t3_c3p80e","subreddit_id":"t5_2s3qj","body":"So fake","body_html":"<div class=\"md\"><p>So fake</p>\n</div>","permalink":"/r/Bitcoin/comments/c3p80e/eleven/ertqb2y/","name":"t1_ertqb2y","created":1561278779,"created_utc":1561249979,"subreddit_name_prefixed":"r/Bitcoin","depth":0},{"ups":1,"link_id":"t3_c3p80e","id":"erttel6","author":"Diezzel","parent_id":"t3_c3p80e","subreddit_id":"t5_2s3qj","body":"yussss","body_html":"<div class=\"md\"><p>yussss</p>\n</div>","permalink":"/r/Bitcoin/comments/c3p80e/eleven/erttel6/","name":"t1_erttel6","created":1561281518,"created_utc":1561252718,"subreddit_name_prefixed":"r/Bitcoin","depth":0},{"ups":1,"link_id":"t3_c3p80e","id":"ertuzu6","author":"agent_kaleido","parent_id":"t3_c3p80e","subreddit_id":"t5_2s3qj","body":"Mmmm...hash Bitcoins","body_html":"<div class=\"md\"><p>Mmmm...hash Bitcoins</p>\n</div>","permalink":"/r/Bitcoin/comments/c3p80e/eleven/ertuzu6/","name":"t1_ertuzu6","created":1561282888,"created_utc":1561254088,"subreddit_name_prefixed":"r/Bitcoin","depth":0},{"ups":1,"link_id":"t3_c3p80e","id":"eru50b6","author":"Mercurio_Arboria","parent_id":"t3_c3p80e","subreddit_id":"t5_2s3qj","body":"One of my favorites, both then and now!","body_html":"<div class=\"md\"><p>One of my favorites, both then and now!</p>\n</div>","permalink":"/r/Bitcoin/comments/c3p80e/eleven/eru50b6/","name":"t1_eru50b6","created":1561292080,"created_utc":1561263280,"subreddit_name_prefixed":"r/Bitcoin","depth":0},{"ups":1,"link_id":"t3_c3p80e","id":"eru7mv6","author":"989x4000","parent_id":"t3_c3p80e","subreddit_id":"t5_2s3qj","body":"Kind of looks like a boy wearing a dress.","body_html":"<div class=\"md\"><p>Kind of looks like a boy wearing a dress.</p>\n</div>","permalink":"/r/Bitcoin/comments/c3p80e/eleven/eru7mv6/","name":"t1_eru7mv6","created":1561294910,"created_utc":1561266110,"subreddit_name_prefixed":"r/Bitcoin","depth":0},{"ups":1,"link_id":"t3_c3p80e","id":"eru80mw","author":"Fitnessisback","parent_id":"t3_c3p80e","subreddit_id":"t5_2s3qj","body":"What comes after 11k ? 5k or 15k ? :)","body_html":"<div class=\"md\"><p>What comes after 11k ? 5k or 15k ? :)</p>\n</div>","permalink":"/r/Bitcoin/comments/c3p80e/eleven/eru80mw/","name":"t1_eru80mw","created":1561295351,"created_utc":1561266551,"subreddit_name_prefixed":"r/Bitcoin","depth":0},{"ups":1,"link_id":"t3_c3p80e","id":"eruadoj","author":"ruwanprasad31","parent_id":"t3_c3p80e","subreddit_id":"t5_2s3qj","body":"Wooow","body_html":"<div class=\"md\"><p>Wooow</p>\n</div>","permalink":"/r/Bitcoin/comments/c3p80e/eleven/eruadoj/","name":"t1_eruadoj","created":1561298213,"created_utc":1561269413,"subreddit_name_prefixed":"r/Bitcoin","depth":0},{"ups":1,"link_id":"t3_c3p80e","id":"erult3r","author":"Joh9IeCa","parent_id":"t3_c3p80e","subreddit_id":"t5_2s3qj","body":"Just eleven ...","body_html":"<div class=\"md\"><p>Just eleven ...</p>\n</div>","permalink":"/r/Bitcoin/comments/c3p80e/eleven/erult3r/","name":"t1_erult3r","created":1561316031,"created_utc":1561287231,"subreddit_name_prefixed":"r/Bitcoin","depth":0},{"ups":1,"link_id":"t3_c3p80e","id":"erumokn","author":"happymondays18","parent_id":"t3_c3p80e","subreddit_id":"t5_2s3qj","body":"Looks like a 7-11.  to add to the mystery","body_html":"<div class=\"md\"><p>Looks like a 7-11.  to add to the mystery</p>\n</div>","permalink":"/r/Bitcoin/comments/c3p80e/eleven/erumokn/","name":"t1_erumokn","created":1561317360,"created_utc":1561288560,"subreddit_name_prefixed":"r/Bitcoin","depth":0},{"ups":1,"link_id":"t3_c3p80e","id":"erxluql","author":"w4r7ock","parent_id":"t3_c3p80e","subreddit_id":"t5_2s3qj","body":"This is an excellent meme.","body_html":"<div class=\"md\"><p>This is an excellent meme.</p>\n</div>","permalink":"/r/Bitcoin/comments/c3p80e/eleven/erxluql/","name":"t1_erxluql","created":1561416820,"created_utc":1561388020,"subreddit_name_prefixed":"r/Bitcoin","depth":0},{"ups":1,"link_id":"t3_c3p80e","replies":[{"ups":2,"link_id":"t3_c3p80e","id":"ersxxw8","author":"Torkiliuz","parent_id":"t1_ersfly8","subreddit_id":"t5_2s3qj","body":"It's from the TV Show \"Stranger Things\"","body_html":"<div class=\"md\"><p>It&#39;s from the TV Show &quot;Stranger Things&quot;</p>\n</div>","permalink":"/r/Bitcoin/comments/c3p80e/eleven/ersxxw8/","name":"t1_ersxxw8","created":1561255933,"created_utc":1561227133,"subreddit_name_prefixed":"r/Bitcoin","depth":2}],"id":"ersba9o","author":"polsymtas","parent_id":"t3_c3p80e","subreddit_id":"t5_2s3qj","body":"This is my fav Bitcoin price meme!\n\n&#x200B;\n\nIt also reminds me I need to update this video  [https://www.youtube.com/watch?v=f\\_BUajML2KY](https://www.youtube.com/watch?v=f_BUajML2KY)  with Zuckerbergs face at the end","body_html":"<div class=\"md\"><p>This is my fav Bitcoin price meme!</p>\n\n<p>&#x200B;</p>\n\n<p>It also reminds me I need to update this video  <a href=\"https://www.youtube.com/watch?v=f_BUajML2KY\">https://www.youtube.com/watch?v=f_BUajML2KY</a>  with Zuckerbergs face at the end</p>\n</div>","permalink":"/r/Bitcoin/comments/c3p80e/eleven/ersba9o/","name":"t1_ersba9o","created":1561237161,"created_utc":1561208361,"subreddit_name_prefixed":"r/Bitcoin","depth":0},{"ups":1,"link_id":"t3_c3p80e","id":"ersn32j","author":"kingoffish","parent_id":"t3_c3p80e","subreddit_id":"t5_2s3qj","body":"I’m accepting bitcoin donations","body_html":"<div class=\"md\"><p>I’m accepting bitcoin donations</p>\n</div>","permalink":"/r/Bitcoin/comments/c3p80e/eleven/ersn32j/","name":"t1_ersn32j","created":1561247604,"created_utc":1561218804,"subreddit_name_prefixed":"r/Bitcoin","depth":0},{"ups":0,"link_id":"t3_c3p80e","replies":[{"ups":0,"link_id":"t3_c3p80e","id":"ersjkfg","author":"kousi","parent_id":"t1_ersifs4","subreddit_id":"t5_2s3qj","body":"lol","body_html":"<div class=\"md\"><p>lol</p>\n</div>","permalink":"/r/Bitcoin/comments/c3p80e/eleven/ersjkfg/","name":"t1_ersjkfg","created":1561244754,"created_utc":1561215954,"subreddit_name_prefixed":"r/Bitcoin","depth":2}],"id":"ershrj1","author":"blose1","parent_id":"t3_c3p80e","subreddit_id":"t5_2s3qj","body":"Funny like I just watched it getting 11k and then going to 10.500 in like 60 seconds. This is not currency anymore, just speculative financial instrument.. What a shame.","body_html":"<div class=\"md\"><p>Funny like I just watched it getting 11k and then going to 10.500 in like 60 seconds. This is not currency anymore, just speculative financial instrument.. What a shame.</p>\n</div>","permalink":"/r/Bitcoin/comments/c3p80e/eleven/ershrj1/","name":"t1_ershrj1","created":1561243229,"created_utc":1561214429,"subreddit_name_prefixed":"r/Bitcoin","depth":0},{"ups":-1,"link_id":"t3_c3p80e","id":"ersdsxs","author":"DontTrustJack","parent_id":"t3_c3p80e","subreddit_id":"t5_2s3qj","body":"Tether printer keeps on delivering! Lets goo 20k next","body_html":"<div class=\"md\"><p>Tether printer keeps on delivering! Lets goo 20k next</p>\n</div>","permalink":"/r/Bitcoin/comments/c3p80e/eleven/ersdsxs/","name":"t1_ersdsxs","created":1561239703,"created_utc":1561210903,"subreddit_name_prefixed":"r/Bitcoin","depth":0},{"ups":0,"link_id":"t3_c3p80e","id":"ertpq8v","author":"NotGonnaGetBanned","parent_id":"t3_c3p80e","subreddit_id":"t5_2s3qj","body":"That's one ugly dude.","body_html":"<div class=\"md\"><p>That&#39;s one ugly dude.</p>\n</div>","permalink":"/r/Bitcoin/comments/c3p80e/eleven/ertpq8v/","name":"t1_ertpq8v","created":1561278270,"created_utc":1561249470,"subreddit_name_prefixed":"r/Bitcoin","depth":0},{"ups":0,"link_id":"t3_c3p80e","id":"erualo5","author":"[deleted]","parent_id":"t3_c3p80e","subreddit_id":"t5_2s3qj","body":"[removed]","body_html":"<div class=\"md\"><p>[removed]</p>\n</div>","permalink":"/r/Bitcoin/comments/c3p80e/eleven/erualo5/","name":"t1_erualo5","created":1561298497,"created_utc":1561269697,"subreddit_name_prefixed":"r/Bitcoin","depth":0},{"ups":-1,"link_id":"t3_c3p80e","id":"ersev76","author":"noeeel","parent_id":"t3_c3p80e","subreddit_id":"t5_2s3qj","body":"This is Elf from stranger things! loving this one, as good as bitcoin","body_html":"<div class=\"md\"><p>This is Elf from stranger things! loving this one, as good as bitcoin</p>\n</div>","permalink":"/r/Bitcoin/comments/c3p80e/eleven/ersev76/","name":"t1_ersev76","created":1561240691,"created_utc":1561211891,"subreddit_name_prefixed":"r/Bitcoin","depth":0},{"ups":-3,"link_id":"t3_c3p80e","id":"ersk669","author":"TheWorldsEndingBitch","parent_id":"t3_c3p80e","subreddit_id":"t5_2s3qj","body":"who gives a crap","body_html":"<div class=\"md\"><p>who gives a crap</p>\n</div>","permalink":"/r/Bitcoin/comments/c3p80e/eleven/ersk669/","name":"t1_ersk669","created":1561245255,"created_utc":1561216455,"subreddit_name_prefixed":"r/Bitcoin","depth":0}]}