{"subreddit":{"display_name":"AdvancedFitness"},"subreddit_loc":"AdvancedFitness","selftext":"5 лет назад я действительно начал заниматься здоровьем, фитнесом и наукой, стоящей за этим. Я думаю, что хотел бы перейти в спортивную карьеру и заняться спортом, и одна идея, которая постоянно появляется, - это стать тренером по силе и физической подготовке, работая с элитными атлетами, а не просто с личным тренером в спортзале. Я рассчитываю поступить в университет в качестве зрелого студента, чтобы получить ученую степень в области спортивной науки, но, кажется, есть несколько вариантов, и я не уверен, что лучше всего подходит, или который бы охватил меня более широко, если мои интересы немного изменятся во время курс. Я думаю, что это мои основные варианты:\n\nСпорт и физические науки Bsc\n\nФизкультура и спорт и физические науки Bsc\n\nСпортивная тренерская наука Bsc\n\nМне было бы очень интересно услышать от любого, кто изучает / завершил одну из этих или аналогичных степеней и в какой карьере вы сейчас находитесь. Любой вклад приветствуется!\nБольшое спасибо!!","title":"29 и рассматривая карьеру в профессиональном спорте и упражнениях ... либо в качестве тренера S & C, работающего с профессиональными спортсменами. Или в научно обоснованной исследовательской стороне вещей. Любой совет по моим вариантам?","subreddit_name_prefixed":"r/AdvancedFitness","ups":43,"created":1565204246,"link_flair_background_color":"","id":"cn4avd","author":{"name":"elroy_starr"},"permalink":"/r/AdvancedFitness/comments/cn4avd/29_and_considering_a_career_in_professional_sport/","url":"https://www.reddit.com/r/AdvancedFitness/comments/cn4avd/29_and_considering_a_career_in_professional_sport/","created_utc":1565175446}