{"subreddit":{"display_name":"nutrition"},"subreddit_loc":"питание","selftext":"Итак, что я понимаю из этой доски, это то, что нагревательные масла выделяют канцерогенные соединения, если они выше точки дымообразования\nЕсли я разогреваю овощи на сковороде без масла (только для вегетарианцев), превращает ли это вегетарианство во что-то вредное?\n\nКроме того, какое масло лучше всего готовить или альтернативу маслу?","title":"Отопительные овощи - как?","subreddit_name_prefixed":"r/nutrition","ups":28,"created":1551112559,"link_flair_background_color":"","id":"auizzl","author":{"name":"baredditki"},"permalink":"/r/nutrition/comments/auizzl/heating_veggies_how/","url":"https://www.reddit.com/r/nutrition/comments/auizzl/heating_veggies_how/","created_utc":1551083759}