{"subreddit":{"display_name":"nutrition"},"subreddit_loc":"питание","selftext":"например\nСделал бы фруктовый пунш (вода, фрукты, стевия, все вареные), а затем удаление фруктов дал бы мне напиток с 0 калориями с обилием минералов?","title":"Если кипяченые фрукты / овощи растворяют питательные вещества в воде: даст ли выпить только оставшуюся жидкость 0-калорийный напиток с витаминами и минералами?","subreddit_name_prefixed":"r/nutrition","ups":106,"created":1572738141,"link_flair_background_color":"","id":"dqlvli","author":{"name":"Morpheusydro"},"permalink":"/r/nutrition/comments/dqlvli/if_boiling_fruitsvegetables_dissolves_the/","url":"https://www.reddit.com/r/nutrition/comments/dqlvli/if_boiling_fruitsvegetables_dissolves_the/","created_utc":1572709341}