{"subreddit":{"display_name":"4chan"},"subreddit_loc":"4chan","selftext":"","title":"Анон задает большие вопросы","subreddit_name_prefixed":"r/4chan","ups":21858,"created":1553586188,"link_flair_background_color":"","id":"b5ib6a","author":{"name":"delightfulporcupine"},"permalink":"/r/4chan/comments/b5ib6a/anon_asks_the_big_questions/","url":"https://i.redd.it/d4w3y118qco21.jpg","created_utc":1553557388,"replies":[{"ups":2146,"link_id":"t3_b5ib6a","replies":[{"ups":11,"link_id":"t3_b5ib6a","replies":[{"ups":16,"link_id":"t3_b5ib6a","id":"ejehrz4","author":"vikingakonungen","parent_id":"t1_ejecdh4","subreddit_id":"t5_2qh4w","body":"Я никогда не видел сингл офисного эпизода. Ama","body_html":"<div class = \"md\"> <p> Я никогда не видел ни одного эпизода в офисе. Ама </p>\n</DIV>","permalink":"/r/4chan/comments/b5ib6a/anon_asks_the_big_questions/ejehrz4/","name":"t1_ejehrz4","created":1553614166,"created_utc":1553585366,"subreddit_name_prefixed":"r/4chan","depth":4},{"ups":9,"link_id":"t3_b5ib6a","id":"ejecot8","author":"Booyahhayoob","parent_id":"t1_ejecdh4","subreddit_id":"t5_2qh4w","body":"* хватает попкорн *","body_html":"<div class = \"md\"> <p> <em> захватывает попкорн </em> </p>\n</DIV>","permalink":"/r/4chan/comments/b5ib6a/anon_asks_the_big_questions/ejecot8/","name":"t1_ejecot8","created":1553607243,"created_utc":1553578443,"subreddit_name_prefixed":"r/4chan","depth":4}],"id":"ejebnub","author":"[deleted]","parent_id":"t1_ejeamzm","subreddit_id":"t5_2qh4w","body":"[Удалено]","body_html":"<div class = \"md\"> <p> [удалено] </p>\n</DIV>","permalink":"/r/4chan/comments/b5ib6a/anon_asks_the_big_questions/ejebnub/","name":"t1_ejebnub","created":1553606071,"created_utc":1553577271,"subreddit_name_prefixed":"r/4chan","depth":2}],"id":"ejdrffv","author":"Pyrrhape","parent_id":"t3_b5ib6a","subreddit_id":"t5_2qh4w","body":"Должно быть, она сделала то же самое в Вудстоке","body_html":"<div class = \"md\"> <p> Она, должно быть, сделала то же самое в Вудстоке </p>\n</DIV>","permalink":"/r/4chan/comments/b5ib6a/anon_asks_the_big_questions/ejdrffv/","name":"t1_ejdrffv","created":1553589175,"created_utc":1553560375,"subreddit_name_prefixed":"r/4chan","depth":0},{"ups":1096,"link_id":"t3_b5ib6a","replies":[{"ups":7,"link_id":"t3_b5ib6a","id":"ejekpii","author":"dutch_penguin","parent_id":"t1_ejecumt","subreddit_id":"t5_2qh4w","body":"Герпес не исчезает от антибиотиков.","body_html":"<div class = \"md\"> <p> Герпес не исчезает от антибиотиков. </p>\n</DIV>","permalink":"/r/4chan/comments/b5ib6a/anon_asks_the_big_questions/ejekpii/","name":"t1_ejekpii","created":1553618980,"created_utc":1553590180,"subreddit_name_prefixed":"r/4chan","depth":2}],"id":"ejduzh0","author":"[deleted]","parent_id":"t3_b5ib6a","subreddit_id":"t5_2qh4w","body":"Это звучит здорово, но все это не похоже на то, как std волшебным образом исчезают, когда они становятся пожилыми.","body_html":"<div class = \"md\"> <p> Звучит великолепно, но все это не похоже на то, что std волшебным образом исчезают, когда они становятся пожилыми. </Р>\n</DIV>","permalink":"/r/4chan/comments/b5ib6a/anon_asks_the_big_questions/ejduzh0/","name":"t1_ejduzh0","created":1553591796,"created_utc":1553562996,"subreddit_name_prefixed":"r/4chan","depth":0},{"ups":1065,"link_id":"t3_b5ib6a","replies":[{"ups":17,"link_id":"t3_b5ib6a","id":"ejei5z1","author":"andrewpost","parent_id":"t1_eje9wpm","subreddit_id":"t5_2qh4w","body":"Seded's Feed & Seed. Какая блестящая синусоидальная шутка.","body_html":"<div class = \"md\"> <p> Sneed's Feed & Seed. Какая блестящая шутка, защищенная от цензуры. </P>\n</DIV>","permalink":"/r/4chan/comments/b5ib6a/anon_asks_the_big_questions/ejei5z1/","name":"t1_ejei5z1","created":1553614786,"created_utc":1553585986,"subreddit_name_prefixed":"r/4chan","depth":2}],"id":"ejdxzvc","author":"firtlast","parent_id":"t3_b5ib6a","subreddit_id":"t5_2qh4w","body":"Джонс Барбекю и массаж ног","body_html":"<div class = \"md\"> <p> Джонс Барбекю и массаж ног </p>\n</DIV>","permalink":"/r/4chan/comments/b5ib6a/anon_asks_the_big_questions/ejdxzvc/","name":"t1_ejdxzvc","created":1553594017,"created_utc":1553565217,"subreddit_name_prefixed":"r/4chan","depth":0},{"ups":545,"link_id":"t3_b5ib6a","replies":[{"ups":13,"link_id":"t3_b5ib6a","id":"ejewzct","author":"BiochemGuitarTurtle","parent_id":"t1_ejefguu","subreddit_id":"t5_2qh4w","body":"У меня есть такой друг. Веселый парень, полная шлюха. Он и мой сосед по комнате в то время работали в одном ресторане вместе с группой друзей. Мы всегда дразнили его, потому что он ударил по какой-то женщине лет пятидесяти, которая там работала, он думал, что это весело.","body_html":"<div class = \"md\"> <p> У меня есть такой же друг. Веселый парень, полная шлюха. Он и мой сосед по комнате в то время работали в одном ресторане вместе с группой друзей. Мы всегда дразнили его, потому что он ударил какую-то даму в ее конце 50-х, которая работала там, он думал, что это было весело. </P>\n</DIV>","permalink":"/r/4chan/comments/b5ib6a/anon_asks_the_big_questions/ejewzct/","name":"t1_ejewzct","created":1553634408,"created_utc":1553605608,"subreddit_name_prefixed":"r/4chan","depth":2}],"id":"ejdtifq","author":"sactbrat1","parent_id":"t3_b5ib6a","subreddit_id":"t5_2qh4w","body":"На самом деле это один из наиболее правдоподобных, которые я видел.","body_html":"<div class = \"md\"> <p> На самом деле это один из наиболее правдоподобных из тех, что я видел. </p>\n</DIV>","permalink":"/r/4chan/comments/b5ib6a/anon_asks_the_big_questions/ejdtifq/","name":"t1_ejdtifq","created":1553590715,"created_utc":1553561915,"subreddit_name_prefixed":"r/4chan","depth":0},{"ups":402,"link_id":"t3_b5ib6a","replies":[{"ups":23,"link_id":"t3_b5ib6a","replies":[{"ups":19,"link_id":"t3_b5ib6a","replies":[{"ups":8,"link_id":"t3_b5ib6a","replies":[{"ups":10,"link_id":"t3_b5ib6a","id":"ejedc0u","author":"dietcokehoe","parent_id":"t1_ejecwdd","subreddit_id":"t5_2qh4w","body":"О, да, да, есть большая шутка, которая высмеивает британцев за то, что их правительство расправляется со свободой и не имеет лицензий. Это не очень хорошее описание, но если вы гуглите «о, приятель, вы получили лицензию», вы найдете хорошие примеры","body_html":"<div class = \"md\"> <p> О, да, да, есть большая шутка, которая высмеивает британцев за то, что их правительство расправляется со свободой и не имеет лицензий. Это не очень хорошее описание, но если вы поищите в Google «у меня приятель, у вас есть лицензия», вы найдете хорошие примеры </p>\n</DIV>","permalink":"/r/4chan/comments/b5ib6a/anon_asks_the_big_questions/ejedc0u/","name":"t1_ejedc0u","created":1553608031,"created_utc":1553579231,"subreddit_name_prefixed":"r/4chan","depth":8}],"id":"ejecn9n","author":"dietcokehoe","parent_id":"t1_ejechuj","subreddit_id":"t5_2qh4w","body":"Вы ... не знаете британский лицензионный мем?","body_html":"<div class = \"md\"> <p> А вы ... не знаете британский мем о лояльности? </p>\n</DIV>","permalink":"/r/4chan/comments/b5ib6a/anon_asks_the_big_questions/ejecn9n/","name":"t1_ejecn9n","created":1553607193,"created_utc":1553578393,"subreddit_name_prefixed":"r/4chan","depth":6}],"id":"ejebdnx","author":"dietcokehoe","parent_id":"t1_eje7nvv","subreddit_id":"t5_2qh4w","body":"Ни у кого нет хорошего мексиканского кулинарного помощника","body_html":"<div class = \"md\"> <p> Bc ни у кого нет хорошего помощника по мексиканской кухне </p>\n</DIV>","permalink":"/r/4chan/comments/b5ib6a/anon_asks_the_big_questions/ejebdnx/","name":"t1_ejebdnx","created":1553605764,"created_utc":1553576964,"subreddit_name_prefixed":"r/4chan","depth":4},{"ups":7,"link_id":"t3_b5ib6a","id":"eje8x64","author":"Thor-Loki-1","parent_id":"t1_eje7nvv","subreddit_id":"t5_2qh4w","body":"Вы не спросили меня, мой мужчина. Позвольте мне вернуться на лодке.\n\nНадеюсь, вам нравится это острым.","body_html":"<div class = \"md\"> <p> Вы не спросили меня, мой мужчина. Позвольте мне вернуться на лодке. </P>\n\n<p> Надеюсь, вам нравится острый. </p>\n</DIV>","permalink":"/r/4chan/comments/b5ib6a/anon_asks_the_big_questions/eje8x64/","name":"t1_eje8x64","created":1553603237,"created_utc":1553574437,"subreddit_name_prefixed":"r/4chan","depth":4}],"id":"eje5g0g","author":"Thor-Loki-1","parent_id":"t1_eje1jfo","subreddit_id":"t5_2qh4w","body":"Это, вероятно, также произносится как \"Хей-соус\".\n\nЧто может объяснить несколько вещей.\n\nЯ имею в виду, что любой может приготовить мексиканский. Это мясо, фасоль, рис, иногда приправленные соусом. Легко.","body_html":"<div class = \"md\"> <p> Это, вероятно, также произносится как \"Hay-soous\". </p>\n\n<p> Что может объяснить несколько вещей. </p>\n\n<p> Я имею в виду, что любой может приготовить мексиканское блюдо. Это мясо, фасоль, рис, иногда приправленные соусом. Легко. </P>\n</DIV>","permalink":"/r/4chan/comments/b5ib6a/anon_asks_the_big_questions/eje5g0g/","name":"t1_eje5g0g","created":1553599949,"created_utc":1553571149,"subreddit_name_prefixed":"r/4chan","depth":2},{"ups":8,"link_id":"t3_b5ib6a","id":"eje58n6","author":"goody2shoos","parent_id":"t1_eje1jfo","subreddit_id":"t5_2qh4w","body":"положи его обратно в кроватку, бабушка","body_html":"<div class = \"md\"> <p> положи его обратно в кроватку, бабушка </p>\n</DIV>","permalink":"/r/4chan/comments/b5ib6a/anon_asks_the_big_questions/eje58n6/","name":"t1_eje58n6","created":1553599774,"created_utc":1553570974,"subreddit_name_prefixed":"r/4chan","depth":2}],"id":"ejdskht","author":"DerekSavoc","parent_id":"t3_b5ib6a","subreddit_id":"t5_2qh4w","body":"Иисус положил его обратно в кроватку бабушки.","body_html":"<div class = \"md\"> <p> Иисус положил его обратно в кроватку бабушки. </p>\n</DIV>","permalink":"/r/4chan/comments/b5ib6a/anon_asks_the_big_questions/ejdskht/","name":"t1_ejdskht","created":1553590019,"created_utc":1553561219,"subreddit_name_prefixed":"r/4chan","depth":0},{"ups":403,"link_id":"t3_b5ib6a","replies":[{"ups":57,"link_id":"t3_b5ib6a","replies":[{"ups":17,"link_id":"t3_b5ib6a","id":"eje8zip","author":"G00DLuck","parent_id":"t1_eje8sbv","subreddit_id":"t5_2qh4w","body":"Потому что она не 93","body_html":"<div class = \"md\"> <p> Потому что она не 93 </p>\n</DIV>","permalink":"/r/4chan/comments/b5ib6a/anon_asks_the_big_questions/eje8zip/","name":"t1_eje8zip","created":1553603302,"created_utc":1553574502,"subreddit_name_prefixed":"r/4chan","depth":4}],"id":"eje83t5","author":"Bortles_da_beast","parent_id":"t1_eje3cy0","subreddit_id":"t5_2qh4w","body":"Насколько сложно это трахнуть и 85-летней женщине?","body_html":"<div class = \"md\"> <p> Насколько сложно трахаться с 85-летней женщиной? </p>\n</DIV>","permalink":"/r/4chan/comments/b5ib6a/anon_asks_the_big_questions/eje83t5/","name":"t1_eje83t5","created":1553602432,"created_utc":1553573632,"subreddit_name_prefixed":"r/4chan","depth":2}],"id":"ejdxa5c","author":"MarjoeCrawley","parent_id":"t3_b5ib6a","subreddit_id":"t5_2qh4w","body":"Мне нравится, что даже в истории с фальшивой задницей этот ОП занял 3 года, чтобы трахнуть 78-летнюю женщину","body_html":"<div class = \"md\"> <p> Мне нравится, что даже в истории с фальшивой задницей потребовалось 3 года, чтобы трахнуть 78-летнюю женщину </p>\n</DIV>","permalink":"/r/4chan/comments/b5ib6a/anon_asks_the_big_questions/ejdxa5c/","name":"t1_ejdxa5c","created":1553593485,"created_utc":1553564685,"subreddit_name_prefixed":"r/4chan","depth":0},{"ups":146,"link_id":"t3_b5ib6a","replies":[{"ups":18,"link_id":"t3_b5ib6a","id":"ejebbqg","author":"aureator","parent_id":"t1_eje0d26","subreddit_id":"t5_2qh4w","body":"удалить этого племянника","body_html":"<div class = \"md\"> <p> удалите этого племянника </p>\n</DIV>","permalink":"/r/4chan/comments/b5ib6a/anon_asks_the_big_questions/ejebbqg/","name":"t1_ejebbqg","created":1553605708,"created_utc":1553576908,"subreddit_name_prefixed":"r/4chan","depth":2}],"id":"ejdwysd","author":"[deleted]","parent_id":"t3_b5ib6a","subreddit_id":"t5_2qh4w","body":"[Удалено]","body_html":"<div class = \"md\"> <p> [удалено] </p>\n</DIV>","permalink":"/r/4chan/comments/b5ib6a/anon_asks_the_big_questions/ejdwysd/","name":"t1_ejdwysd","created":1553593253,"created_utc":1553564453,"subreddit_name_prefixed":"r/4chan","depth":0},{"ups":120,"link_id":"t3_b5ib6a","replies":[{"ups":46,"link_id":"t3_b5ib6a","replies":[{"ups":25,"link_id":"t3_b5ib6a","id":"eje48l7","author":"EthanBradberry70","parent_id":"t1_eje35wr","subreddit_id":"t5_2qh4w","body":"Гадкий.","body_html":"<div class = \"md\"> <p> Гадкий. </p>\n</DIV>","permalink":"/r/4chan/comments/b5ib6a/anon_asks_the_big_questions/eje48l7/","name":"t1_eje48l7","created":1553598922,"created_utc":1553570122,"subreddit_name_prefixed":"r/4chan","depth":4},{"ups":8,"link_id":"t3_b5ib6a","id":"eje4ty1","author":"[deleted]","parent_id":"t1_eje35wr","subreddit_id":"t5_2qh4w","body":"недочеловеческий","body_html":"<div class = \"md\"> <p> недочеловек </p>\n</DIV>","permalink":"/r/4chan/comments/b5ib6a/anon_asks_the_big_questions/eje4ty1/","name":"t1_eje4ty1","created":1553599428,"created_utc":1553570628,"subreddit_name_prefixed":"r/4chan","depth":4}],"id":"eje2ocm","author":"nigby69","parent_id":"t1_eje1hwv","subreddit_id":"t5_2qh4w","body":"Какое у тебя оправдание тогда?","body_html":"<div class = \"md\"> <p> Какое у вас оправдание? </p>\n</DIV>","permalink":"/r/4chan/comments/b5ib6a/anon_asks_the_big_questions/eje2ocm/","name":"t1_eje2ocm","created":1553597632,"created_utc":1553568832,"subreddit_name_prefixed":"r/4chan","depth":2}],"id":"ejdx6vb","author":"1fastman1","parent_id":"t3_b5ib6a","subreddit_id":"t5_2qh4w","body":"Прошли годы, и она не изменилась с тех пор, как Вудсток","body_html":"<div class = \"md\"> <p> Прошли годы, и она не изменилась с тех пор, как Вудсток </p>\n</DIV>","permalink":"/r/4chan/comments/b5ib6a/anon_asks_the_big_questions/ejdx6vb/","name":"t1_ejdx6vb","created":1553593417,"created_utc":1553564617,"subreddit_name_prefixed":"r/4chan","depth":0},{"ups":47,"link_id":"t3_b5ib6a","replies":[{"ups":40,"link_id":"t3_b5ib6a","id":"eje6sze","author":"[deleted]","parent_id":"t1_eje4dn0","subreddit_id":"t5_2qh4w","body":"Готэм","body_html":"<div class = \"md\"> <p> Gotem </p>\n</DIV>","permalink":"/r/4chan/comments/b5ib6a/anon_asks_the_big_questions/eje6sze/","name":"t1_eje6sze","created":1553601179,"created_utc":1553572379,"subreddit_name_prefixed":"r/4chan","depth":2},{"ups":9,"link_id":"t3_b5ib6a","id":"eje7wns","author":"jaysontatyums","parent_id":"t1_eje4dn0","subreddit_id":"t5_2qh4w","body":"я позволю это","body_html":"<div class = \"md\"> <p> я разрешаю </p>\n</DIV>","permalink":"/r/4chan/comments/b5ib6a/anon_asks_the_big_questions/eje7wns/","name":"t1_eje7wns","created":1553602240,"created_utc":1553573440,"subreddit_name_prefixed":"r/4chan","depth":2}],"id":"ejdz4ui","author":"Jackisking1","parent_id":"t3_b5ib6a","subreddit_id":"t5_2qh4w","body":"Я тоже трахнул 70 лет, и секс был великолепен, мне было 25 лет в то время","body_html":"<div class = \"md\"> <p> Я тоже трахнул 70-летний, и секс был великолепным, мне тогда было 25 лет </p>\n</DIV>","permalink":"/r/4chan/comments/b5ib6a/anon_asks_the_big_questions/ejdz4ui/","name":"t1_ejdz4ui","created":1553594881,"created_utc":1553566081,"subreddit_name_prefixed":"r/4chan","depth":0},{"ups":49,"link_id":"t3_b5ib6a","replies":[{"ups":13,"link_id":"t3_b5ib6a","id":"ejeb3u9","author":"[deleted]","parent_id":"t1_eje6pfg","subreddit_id":"t5_2qh4w","body":"Если вы не можете промокнуть от привлекательности, по крайней мере, вы можете подождать, пока они станут мокрыми от менструации.","body_html":"<div class = \"md\"> <p> Если вы не можете намочить их от влечения, по крайней мере, вы можете подождать, пока они станут мокрыми от менструации. </p>\n</DIV>","permalink":"/r/4chan/comments/b5ib6a/anon_asks_the_big_questions/ejeb3u9/","name":"t1_ejeb3u9","created":1553605475,"created_utc":1553576675,"subreddit_name_prefixed":"r/4chan","depth":2}],"id":"eje0m5m","author":"earthquake26","parent_id":"t3_b5ib6a","subreddit_id":"t5_2qh4w","body":"Я мог бы стряхнуть синие волосы на работе, на которой работал. Почти дошел до этого, но бросил. Потому что я поняла, что мне тогда было 22 года, и у меня появилась киска, которая не переставала менструировать.","body_html":"<div class = \"md\"> <p> Я мог сам постучать в синие волосы на работе, на которой работал. Почти дошел до этого, но бросил. Потому что я понял, что мне тогда было 22 года, и я мог получить киску, которая не переставала менструировать. </P>\n</DIV>","permalink":"/r/4chan/comments/b5ib6a/anon_asks_the_big_questions/eje0m5m/","name":"t1_eje0m5m","created":1553596021,"created_utc":1553567221,"subreddit_name_prefixed":"r/4chan","depth":0},{"ups":27,"link_id":"t3_b5ib6a","id":"ejdwl85","author":"Sam_Hog","parent_id":"t3_b5ib6a","subreddit_id":"t5_2qh4w","body":"samefag","body_html":"<div class = \"md\"> <p> samefag </p>\n</DIV>","permalink":"/r/4chan/comments/b5ib6a/anon_asks_the_big_questions/ejdwl85/","name":"t1_ejdwl85","created":1553592979,"created_utc":1553564179,"subreddit_name_prefixed":"r/4chan","depth":0},{"ups":28,"link_id":"t3_b5ib6a","id":"ejejsmq","author":"Shacken-Wan","parent_id":"t3_b5ib6a","subreddit_id":"t5_2qh4w","body":"хттпс://и.имгур.ком/у32ФРльг.жпг","body_html":"<div class = \"md\"> <p> <a href=\"https://i.imgur.com/u32FRlg.jpg\"> https://i.imgur.com/u32FRlg.jpg </a> </a р>\n</DIV>","permalink":"/r/4chan/comments/b5ib6a/anon_asks_the_big_questions/ejejsmq/","name":"t1_ejejsmq","created":1553617414,"created_utc":1553588614,"subreddit_name_prefixed":"r/4chan","depth":0},{"ups":24,"link_id":"t3_b5ib6a","id":"eje7udb","author":"JedYorks","parent_id":"t3_b5ib6a","subreddit_id":"t5_2qh4w","body":"Игра с киской несвежая, но игра с печеньем свежая 🍪","body_html":"<div class = \"md\"> <p> Игра с киской устарела, но игра с печеньем свежая 🍪 </p>\n</DIV>","permalink":"/r/4chan/comments/b5ib6a/anon_asks_the_big_questions/eje7udb/","name":"t1_eje7udb","created":1553602176,"created_utc":1553573376,"subreddit_name_prefixed":"r/4chan","depth":0},{"ups":22,"link_id":"t3_b5ib6a","id":"ejdu1vl","author":"Raz3n","parent_id":"t3_b5ib6a","subreddit_id":"t5_2qh4w","body":"Анон не ответил","body_html":"<div class = \"md\"> <p> Анон не ответил </p>\n</DIV>","permalink":"/r/4chan/comments/b5ib6a/anon_asks_the_big_questions/ejdu1vl/","name":"t1_ejdu1vl","created":1553591113,"created_utc":1553562313,"subreddit_name_prefixed":"r/4chan","depth":0},{"ups":24,"link_id":"t3_b5ib6a","id":"eje3dx4","author":"clever_cow","parent_id":"t3_b5ib6a","subreddit_id":"t5_2qh4w","body":"Реальный и гетеросексуальный","body_html":"<div class = \"md\"> <p> Реальный и гетеросексуальный </p>\n</DIV>","permalink":"/r/4chan/comments/b5ib6a/anon_asks_the_big_questions/eje3dx4/","name":"t1_eje3dx4","created":1553598210,"created_utc":1553569410,"subreddit_name_prefixed":"r/4chan","depth":0},{"ups":18,"link_id":"t3_b5ib6a","id":"eje2qa4","author":"I_might_be_weasel","parent_id":"t3_b5ib6a","subreddit_id":"t5_2qh4w","body":"«Теперь об этом повышении ....»","body_html":"<div class = \"md\"> <p> \"Теперь об этом повышении ....\" </p>\n</DIV>","permalink":"/r/4chan/comments/b5ib6a/anon_asks_the_big_questions/eje2qa4/","name":"t1_eje2qa4","created":1553597676,"created_utc":1553568876,"subreddit_name_prefixed":"r/4chan","depth":0},{"ups":15,"link_id":"t3_b5ib6a","id":"eje680d","author":"kur955","parent_id":"t3_b5ib6a","subreddit_id":"t5_2qh4w","body":"серьезно, хотя звучит чертовски дурь tfw не бабушка хиппи, чтобы вставить мой член в ее пожилой киске","body_html":"<div class = \"md\"> <p> серьезно, хотя это звучит чертовски дурно, нет бабушки хиппи, чтобы вставить мой член в ее пожилую киску </p>\n</DIV>","permalink":"/r/4chan/comments/b5ib6a/anon_asks_the_big_questions/eje680d/","name":"t1_eje680d","created":1553600644,"created_utc":1553571844,"subreddit_name_prefixed":"r/4chan","depth":0},{"ups":13,"link_id":"t3_b5ib6a","id":"eje2kkb","author":"Dookiestain_LaFlair","parent_id":"t3_b5ib6a","subreddit_id":"t5_2qh4w","body":"Должен был подавить ее морщинистый пердеть","body_html":"<div class = \"md\"> <p> Надо было скушать ее морщинистый пердун </p>\n</DIV>","permalink":"/r/4chan/comments/b5ib6a/anon_asks_the_big_questions/eje2kkb/","name":"t1_eje2kkb","created":1553597546,"created_utc":1553568746,"subreddit_name_prefixed":"r/4chan","depth":0},{"ups":8,"link_id":"t3_b5ib6a","id":"ejdzyxg","author":"Negrodamu55","parent_id":"t3_b5ib6a","subreddit_id":"t5_2qh4w","body":"Этот парень из семьи Аддамс?","body_html":"<div class = \"md\"> <p> Это парень из семьи Аддамс? </p>\n</DIV>","permalink":"/r/4chan/comments/b5ib6a/anon_asks_the_big_questions/ejdzyxg/","name":"t1_ejdzyxg","created":1553595521,"created_utc":1553566721,"subreddit_name_prefixed":"r/4chan","depth":0},{"ups":7,"link_id":"t3_b5ib6a","id":"ejdrt5n","author":"ThePowerWithinX","parent_id":"t3_b5ib6a","subreddit_id":"t5_2qh4w","body":"Ницца","body_html":"<div class = \"md\"> <p> Nice </p>\n</DIV>","permalink":"/r/4chan/comments/b5ib6a/anon_asks_the_big_questions/ejdrt5n/","name":"t1_ejdrt5n","created":1553589458,"created_utc":1553560658,"subreddit_name_prefixed":"r/4chan","depth":0},{"ups":6,"link_id":"t3_b5ib6a","id":"ejecu9p","author":"[deleted]","parent_id":"t3_b5ib6a","subreddit_id":"t5_2qh4w","body":"По крайней мере, он больше не девственник. ПОЗЖЕ, проигравшие","body_html":"<div class = \"md\"> <p> По крайней мере, он больше не девственник. Поздние неудачники </p>\n</DIV>","permalink":"/r/4chan/comments/b5ib6a/anon_asks_the_big_questions/ejecu9p/","name":"t1_ejecu9p","created":1553607429,"created_utc":1553578629,"subreddit_name_prefixed":"r/4chan","depth":0},{"ups":6,"link_id":"t3_b5ib6a","id":"eje20z9","author":"[deleted]","parent_id":"t3_b5ib6a","subreddit_id":"t5_2qh4w","body":"Это называется Ранняя особенность","body_html":"<div class = \"md\"> <p> Это называется «Раннее специальное предложение» </p>\n</DIV>","permalink":"/r/4chan/comments/b5ib6a/anon_asks_the_big_questions/eje20z9/","name":"t1_eje20z9","created":1553597111,"created_utc":1553568311,"subreddit_name_prefixed":"r/4chan","depth":0}]}